pcapy.cpython-38-x86_64-linux-gnu.so
pcapy_binary-0.11.5.2.dist-info/top_level.txt
pcapy_binary-0.11.5.2.dist-info/WHEEL
pcapy_binary-0.11.5.2.dist-info/RECORD
pcapy_binary-0.11.5.2.dist-info/METADATA
pcapy_binary-0.11.5.2.dist-info/LICENSE
pcapy_binary.libs/libpcap-828cc380.so.1.5.3
pcapy_binary-0.11.5.2.data/data/share/doc/pcapy/pcapy.html
pcapy_binary-0.11.5.2.data/data/share/doc/pcapy/LICENSE
pcapy_binary-0.11.5.2.data/data/share/doc/pcapy/README
pcapy_binary-0.11.5.2.data/data/share/doc/pcapy/tests/96pings.pcap
pcapy_binary-0.11.5.2.data/data/share/doc/pcapy/tests/pcapytests.py
