Metadata-Version: 2.1
Name: pcapy-binary
Version: 0.11.5.2
Summary: Python pcap extension
Home-page: https://github.com/CoreSecurity/pcapy
Author: CORE Security
Author-email: oss@coresecurity.com
Maintainer: CORE Security
Maintainer-email: oss@coresecurity.com
License: Apache modified
Platform: Unix
Platform: Windows
License-File: LICENSE
